{
  "url": "https://github.com/MTES-MCT/trackdechets",
  "name": "trackdechets",
  "description": "Trackdéchets est une solution pour gérer la traçabilité des déchets en toute sécurité. Elle est incubée par la Fabrique Numérique du Ministère de la Transition Écologique et vise à simplifier et sécuriser le suivi des déchets.",
  "language": "TypeScript",
  "features": [
    "Gestion de la traçabilité des déchets",
    "Création et gestion de bordereaux de déchets (BSDA, BSFF, BSVHU)",
    "Signature électronique",
    "Recherche d'entreprises",
    "Gestion des utilisateurs et des rôles",
    "Export de données",
    "Suivi des déchets",
    "Gestion des transporteurs",
    "Gestion des éco-organismes"
  ],
  "audience": "Professionnels",
  "dependencies": [
    "Node.js",
    "Express.js",
    "Apollo Server",
    "Prisma ORM",
    "PostgreSQL",
    "Elasticsearch",
    "React.js",
    "Apollo Client",
    "Typescript"
  ],
  "components": [
    "Backend Node.js / TypeScript avec Express.js et Apollo Server",
    "Frontend React.js / TypeScript",
    "Base de données PostgreSQL",
    "Moteur de recherche Elasticsearch",
    "API REST",
    "Interface graphique (SPA)"
  ],
  "auth": {
    "methods": [
      "email-password",
      "oauth2"
    ]
  },
  "tests": [
    "Intégration tests",
    "Tests unitaires"
  ],
  "workflows": [
    "Build & Test",
    "Integration tests"
  ],
  "lastActivity": "2026-02-10T20:14:04+01:00",
  "status": "active",
  "license": "AGPL-3.0-or-later",
  "hasDocumentation": true,
  "metrics": {
    "stars": null,
    "forks": null,
    "contributors": null,
    "openIssues": null
  },
  "tags": [
    "déchets",
    "traçabilité",
    "environnement",
    "recyclage",
    "gestion des déchets",
    "Node.js",
    "React",
    "TypeScript",
    "PostgreSQL",
    "Elasticsearch"
  ]
}
