{
  "url": "https://github.com/betagouv/api.gouv.fr",
  "name": "api.gouv.fr",
  "description": "api.gouv.fr catalogue les API produites par les administrations françaises. Il permet de découvrir, comprendre et accéder aux API et à leurs producteurs.",
  "language": "JavaScript",
  "features": [
    "API & Intégrations",
    "Gestion documentaire & Fichiers",
    "Recherche & Filtres"
  ],
  "audience": "Professionnels",
  "dependencies": [
    "Next.js",
    "React",
    "Node.js",
    "sass"
  ],
  "components": [
    "React / Next.js",
    "API REST & GraphQL",
    "PostgreSQL & SQL"
  ],
  "auth": {
    "methods": [
      "none"
    ]
  },
  "tests": [
    "Jest",
    "Axe-core (accessibilité)",
    "Broken Link Checker"
  ],
  "workflows": [
    "check-accessibility.yml",
    "check-broken-links.yml",
    "deploy-production.yml",
    "deploy-staging.yml",
    "pre-merge.yml"
  ],
  "lastActivity": "2026-01-07T15:26:55+01:00",
  "status": "active",
  "license": "AGPL-3.0-or-later",
  "hasDocumentation": true,
  "metrics": {
    "stars": 339,
    "forks": 163,
    "contributors": null,
    "openIssues": 33
  },
  "tags": [
    "Données & Open Data",
    "Écosystème beta.gouv / État",
    "Catalogue d'API"
  ]
}
