{
  "url": "https://github.com/SocialGouv/code-du-travail-numerique",
  "name": "code-du-travail-numerique",
  "description": "Ce projet vise à rendre le code du travail plus accessible et compréhensible grâce à des outils numériques. Il fournit des simulateurs, des informations et des modèles de documents pour aider les utilisateurs à naviguer dans le droit du travail.",
  "language": "TypeScript",
  "features": [
    "Recherche & Filtres",
    "Simulation & Calcul",
    "Gestion documentaire & Fichiers",
    "Infographies",
    "Informations légales"
  ],
  "audience": "Grand public",
  "dependencies": [
    "Next.js",
    "pnpm",
    "lerna",
    "publicodes"
  ],
  "components": [
    "React / Next.js",
    "API REST & GraphQL",
    "PostgreSQL & SQL",
    "TypeScript / JavaScript"
  ],
  "auth": {
    "methods": [
      "none"
    ]
  },
  "tests": [
    "Jest",
    "Cypress",
    "Tests e2e"
  ],
  "workflows": [
    "quality.yml"
  ],
  "lastActivity": "2026-03-04T00:00:00Z",
  "status": "active",
  "license": "MIT",
  "hasDocumentation": true,
  "metrics": null,
  "tags": [
    "code du travail",
    "droit du travail",
    "simulateur",
    "Données & Open Data",
    "Écosystème beta.gouv / État",
    "TypeScript",
    "React & Next.js"
  ]
}
