{
  "url": "https://github.com/betagouv/mon-aide-cyber",
  "name": "mon-aide-cyber",
  "description": "MonAideCyber est un service numérique destiné aux entités publiques et privées pour renforcer leur cybersécurité de manière proportionnée et concrète.",
  "language": "TypeScript",
  "features": [
    "Gestion des aidants",
    "Formulaires & Démarches",
    "Sécurité & Conformité",
    "Statistiques & Rapports",
    "Authentification & Accès"
  ],
  "audience": "Professionnels",
  "dependencies": [
    "Express",
    "PostgreSQL",
    "React",
    "knex",
    "jsonwebtoken",
    "zod",
    "date-fns"
  ],
  "components": [
    "React / Next.js",
    "API REST & GraphQL",
    "PostgreSQL & SQL",
    "Microservices & Architecture"
  ],
  "auth": {
    "methods": [
      "email-password",
      "oauth2"
    ]
  },
  "tests": [
    "Vitest",
    "Cypress"
  ],
  "workflows": [
    "checkov.yml",
    "codeql.yml",
    "deploiement.yml",
    "nodejs.yml",
    "storybook-tests.yml"
  ],
  "lastActivity": "2026-03-02T15:21:38+01:00",
  "status": "active",
  "license": "Apache-2.0",
  "hasDocumentation": true,
  "metrics": {
    "stars": 13,
    "forks": 5,
    "contributors": null,
    "openIssues": 1
  },
  "tags": [
    "Sécurité & Auth",
    "Subventions & Finances publiques",
    "diagnostic",
    "Écosystème beta.gouv / État",
    "TypeScript",
    "React & Next.js",
    "Bases de données SQL"
  ]
}
