{
  "url": "https://github.com/mtes-mct/Localiser_Parcelle_Adresse_BAN",
  "name": "Localiser_Parcelle_Adresse_BAN",
  "description": "Cette extension pour QGIS permet de localiser une commune, une section, une parcelle cadastrale ou une adresse postale en interrogeant des services réseau.",
  "language": "Python",
  "features": [
    "Visualisation de données & Cartographie"
  ],
  "audience": "Professionnels",
  "dependencies": [
    "QGIS"
  ],
  "components": [
    "SIG & Géospatial",
    "Microservices & Architecture",
    "Communication HTTP avec des services web"
  ],
  "auth": {
    "methods": [
      "none"
    ]
  },
  "tests": null,
  "workflows": null,
  "lastActivity": "2023-12-07T09:59:52Z",
  "status": "active",
  "license": null,
  "hasDocumentation": true,
  "metrics": {
    "stars": 0,
    "forks": 2,
    "contributors": null,
    "openIssues": 2
  },
  "tags": [
    "SIG & Géospatial",
    "Cadastre",
    "Adresse",
    "Python"
  ]
}
